pypet/__init__.py
pypet/_version.py
pypet/annotations.py
pypet/environment.py
pypet/naturalnaming.py
pypet/parameter.py
pypet/pypetconstants.py
pypet/pypetexceptions.py
pypet/pypetlogging.py
pypet/shareddata.py
pypet/slots.py
pypet/storageservice.py
pypet/trajectory.py
pypet/brian2/__init__.py
pypet/brian2/network.py
pypet/brian2/parameter.py
pypet/logging/debug.ini
pypet/logging/default.ini
pypet/logging/env_config_test.ini
pypet/logging/test.ini
pypet/tests/__init__.py
pypet/tests/_atworema.py
pypet/tests/all_examples.py
pypet/tests/all_multi_core_tests.py
pypet/tests/all_single_core_tests.py
pypet/tests/all_tests.py
pypet/tests/coverage_run.py
pypet/tests/scoop_run.py
pypet/tests/test_all_nose.py
pypet/tests/integration/__init__.py
pypet/tests/integration/envSCOOPdebug.py
pypet/tests/integration/environment_multiproc_test.py
pypet/tests/integration/environment_scoop_test.py
pypet/tests/integration/environment_test.py
pypet/tests/integration/git_check.py
pypet/tests/integration/link_multiproc_test.py
pypet/tests/integration/link_test.py
pypet/tests/integration/logging_multiproc_test.py
pypet/tests/integration/logging_test.py
pypet/tests/integration/merge_test.py
pypet/tests/integration/pipeline_test.py
pypet/tests/integration/removal_and_continue_test.py
pypet/tests/integration/shared_data_test.py
pypet/tests/integration/brian2tests/__init__.py
pypet/tests/integration/brian2tests/another_network_test.py
pypet/tests/integration/brian2tests/hdf5_brian2_test.py
pypet/tests/integration/brian2tests/network_test.py
pypet/tests/profiling/__init__.py
pypet/tests/profiling/creating_run_table.py
pypet/tests/profiling/profiling.py
pypet/tests/testdata/pypet_v0_1b_6.hdf5
pypet/tests/testutils/__init__.py
pypet/tests/testutils/data.py
pypet/tests/testutils/ioutils.py
pypet/tests/unittests/__init__.py
pypet/tests/unittests/annotations_test.py
pypet/tests/unittests/configparse_test.py
pypet/tests/unittests/link_test.py
pypet/tests/unittests/module_test.py
pypet-0.6.0.dist-info/LICENSE
pypet-0.6.0.dist-info/METADATA
pypet-0.6.0.dist-info/WHEEL
pypet-0.6.0.dist-info/top_level.txt
pypet-0.6.0.dist-info/RECORD
